antibp3/blast_binaries/linux/blastp
antibp3/blast_binaries/mac/blastp
antibp3/blast_binaries/windows/blastp.exe
antibp3/blast_db/gramneg/gramneg_db.pdb
antibp3/blast_db/gramneg/gramneg_db.phr
antibp3/blast_db/gramneg/gramneg_db.pin
antibp3/blast_db/gramneg/gramneg_db.pjs
antibp3/blast_db/gramneg/gramneg_db.pot
antibp3/blast_db/gramneg/gramneg_db.psq
antibp3/blast_db/gramneg/gramneg_db.ptf
antibp3/blast_db/gramneg/gramneg_db.pto
antibp3/blast_db/grampos/grampos_db.pdb
antibp3/blast_db/grampos/grampos_db.phr
antibp3/blast_db/grampos/grampos_db.pin
antibp3/blast_db/grampos/grampos_db.pjs
antibp3/blast_db/grampos/grampos_db.pot
antibp3/blast_db/grampos/grampos_db.psq
antibp3/blast_db/grampos/grampos_db.ptf
antibp3/blast_db/grampos/grampos_db.pto
antibp3/blast_db/gramvariable/gramvariable_db.pdb
antibp3/blast_db/gramvariable/gramvariable_db.phr
antibp3/blast_db/gramvariable/gramvariable_db.pin
antibp3/blast_db/gramvariable/gramvariable_db.pjs
antibp3/blast_db/gramvariable/gramvariable_db.pot
antibp3/blast_db/gramvariable/gramvariable_db.psq
antibp3/blast_db/gramvariable/gramvariable_db.ptf
antibp3/blast_db/gramvariable/gramvariable_db.pto
antibp3/model/modelET_GN_aabNC.pkl
antibp3/model/modelRF_GP_aabNC.pkl
antibp3/model/modelSVC_GV_aabNC.pkl
antibp3/motif/GN_motif
antibp3/motif/GP_motif
antibp3/motif/GV_motif
antibp3/perl_scripts/MERCI_motif_locator.pl
antibp3/python_scripts/__init__.py
antibp3/python_scripts/antibp3.py
antibp3-1.3.dist-info/LICENSE.txt
antibp3-1.3.dist-info/METADATA
antibp3-1.3.dist-info/WHEEL
antibp3-1.3.dist-info/entry_points.txt
antibp3-1.3.dist-info/top_level.txt
antibp3-1.3.dist-info/RECORD
