Metadata-Version: 2.1
Name: antibp3
Version: 1.3
Summary: A tool to predict anti-bacterial peptides
Home-page: https://github.com/raghavagps/AntiBP3
License: UNKNOWN
Platform: UNKNOWN
Requires-Python: >=3.6
License-File: LICENSE.txt
Requires-Dist: numpy
Requires-Dist: pandas
Requires-Dist: argparse
